env_printer/__init__.py
env_printer/cli.py
env_printer/post_install.py
env_printer-0.1.2.dist-info/licenses/LICENSE
env_printer-0.1.2.dist-info/METADATA
env_printer-0.1.2.dist-info/WHEEL
env_printer-0.1.2.dist-info/entry_points.txt
env_printer-0.1.2.dist-info/top_level.txt
env_printer-0.1.2.dist-info/RECORD
